QhX/__init__.py
QhX/batch_processor.py
QhX/calculation.py
QhX/data_manager.py
QhX/detection.py
QhX/dynamical_mode.py
QhX/interactive_plot_large_files.py
QhX/iparallelization_solver.py
QhX/light_curve.py
QhX/merge_batch_csv.py
QhX/merge_csv_results.py
QhX/output.py
QhX/output_parallel.py
QhX/parallel_classification.py
QhX/parallelization_solver.py
QhX/processing_utils.py
QhX_dynamical-0.1.0.dist-info/LICENSE.txt
QhX_dynamical-0.1.0.dist-info/METADATA
QhX_dynamical-0.1.0.dist-info/WHEEL
QhX_dynamical-0.1.0.dist-info/top_level.txt
QhX_dynamical-0.1.0.dist-info/RECORD
