Metadata-Version: 2.1
Name: QhX_dynamical
Version: 0.1.0
Summary: QhX_dynamical: Extending QhX with dynamic mode for light curve analysis
Author-email: Andjelka Kovacevic <andjelka.kovacevic@matf.bg.ac.rs>
License: MIT License
Project-URL: Documentation, https://lionandjelka.github.io/QhX_dynamical/introduction.html
Keywords: astronomy,data analysis,light curves,dynamic mode
Classifier: Development Status :: 3 - Alpha
Classifier: Intended Audience :: Science/Research
Classifier: License :: OSI Approved :: MIT License
Classifier: Programming Language :: Python :: 3
Classifier: Programming Language :: Python :: 3.7
Classifier: Programming Language :: Python :: 3.8
Classifier: Programming Language :: Python :: 3.9
Classifier: Programming Language :: Python :: 3.10
Classifier: Operating System :: OS Independent
Requires-Python: >=3.0
License-File: LICENSE.txt
Requires-Dist: numpy
Requires-Dist: pandas
Requires-Dist: scipy
Requires-Dist: scikit-learn
Requires-Dist: scikit-optimize
Requires-Dist: libwwz
Requires-Dist: colorednoise
Requires-Dist: tqdm
Requires-Dist: panel
Requires-Dist: hvplot
Requires-Dist: bokeh
Requires-Dist: datashader
Requires-Dist: pyarrow
Requires-Dist: dask[dataframe]
Requires-Dist: traitlets
Provides-Extra: tests
Requires-Dist: pytest; extra == "tests"
